torch_directml_native.cp39-win_amd64.pyd
torch_directml/DirectML.dll
torch_directml/__init__.py
torch_directml/device.py
torch_directml/csrc/auto_gen_yaml.py
experimental_torch_directml-0.1.13.dev23122022132839.dist-info/LICENSE
experimental_torch_directml-0.1.13.dev23122022132839.dist-info/METADATA
experimental_torch_directml-0.1.13.dev23122022132839.dist-info/NOTICE
experimental_torch_directml-0.1.13.dev23122022132839.dist-info/WHEEL
experimental_torch_directml-0.1.13.dev23122022132839.dist-info/top_level.txt
experimental_torch_directml-0.1.13.dev23122022132839.dist-info/RECORD
