Metadata-Version: 2.1
Name: experimental-torch-directml
Version: 0.1.13.dev23122022132839
Summary: A DirectML backend for hardware acceleration in PyTorch.
Home-page: https://github.com/microsoft/directml
Author: Microsoft Corporation
Author-email: askdirectml@microsoft.com
License: MIT
Project-URL: Bug Tracker, https://github.com/microsoft/directml/issues
Keywords: pytorch,plugin,machine learning,directml,directx,d3d12
Classifier: Development Status :: 5 - Production/Stable
Classifier: Intended Audience :: Developers
Classifier: Intended Audience :: Education
Classifier: Intended Audience :: Science/Research
Classifier: License :: OSI Approved :: MIT License
Classifier: Topic :: Scientific/Engineering
Classifier: Topic :: Scientific/Engineering :: Mathematics
Classifier: Topic :: Scientific/Engineering :: Artificial Intelligence
Classifier: Topic :: Software Development
Classifier: Topic :: Software Development :: Libraries
Classifier: Topic :: Software Development :: Libraries :: Python Modules
Classifier: Programming Language :: C++
Classifier: Programming Language :: Python :: 3
Classifier: Programming Language :: Python :: 3.7
Classifier: Programming Language :: Python :: 3.8
Classifier: Programming Language :: Python :: 3.9
Classifier: Programming Language :: Python :: 3.10
Requires-Python: >=3.7
License-File: LICENSE
License-File: NOTICE
Requires-Dist: torch (==1.13.0)
Requires-Dist: torchvision (==0.14.0)
